outfit/__init__.py
outfit/config_loader.py
outfit/hashicorp/__init__.py
outfit/hashicorp/consul_config.py
outfit/hashicorp/hashicorp_base.py
outfit/hashicorp/vault_config.py
outfit/utils/__init__.py
outfit/utils/collections.py
outfit/utils/db_status.py
outfit/utils/healtchcheck.py
outfit/utils/io.py
outfit/utils/logger.py
python_outfit-0.0.8.dist-info/LICENSE
python_outfit-0.0.8.dist-info/METADATA
python_outfit-0.0.8.dist-info/WHEEL
python_outfit-0.0.8.dist-info/top_level.txt
python_outfit-0.0.8.dist-info/RECORD
